django_eveonline_buyback/__init__.py
django_eveonline_buyback/admin.py
django_eveonline_buyback/apps.py
django_eveonline_buyback/bindings.py
django_eveonline_buyback/forms.py
django_eveonline_buyback/models.py
django_eveonline_buyback/urls.py
django_eveonline_buyback/views.py
django_eveonline_buyback/migrations/0001_initial.py
django_eveonline_buyback/migrations/0002_auto.py
django_eveonline_buyback/migrations/0003_auto_20200822_2128.py
django_eveonline_buyback/migrations/0004_auto_20210220_2112.py
django_eveonline_buyback/migrations/0005_buybacksettings_contract_entity.py
django_eveonline_buyback/migrations/__init__.py
django_eveonline_buyback/templates/django_eveonline_buyback/sidebar.html
django_eveonline_buyback/templates/django_eveonline_buyback/adminlte/buyback.html
django_eveonline_buyback/test/__init__.py
django_eveonline_buyback/test/test_django_eveonline_buyback.py
django_eveonline_buyback-0.0.4.dist-info/LICENSE
django_eveonline_buyback-0.0.4.dist-info/METADATA
django_eveonline_buyback-0.0.4.dist-info/WHEEL
django_eveonline_buyback-0.0.4.dist-info/top_level.txt
django_eveonline_buyback-0.0.4.dist-info/RECORD
